<?xml version="1.0"?>
<groundnet>
  <version>1</version>
  <parkingList>
        <Parking index="0" type="ga" name="Ramp_start_1" lat="N49 40.851124" lon="E12 6.910439" heading="217.66"  radius="10" pushBackRoute="8" airlineCodes="" />
        <Parking index="1" type="ga" name="Ramp_start_2" lat="N49 40.803448" lon="E12 7.011212" heading="233.63"  radius="10" pushBackRoute="17" airlineCodes="" />
        <Parking index="2" type="ga" name="Ramp_start_3" lat="N49 40.769617" lon="E12 7.016389" heading="233.63"  radius="10" pushBackRoute="5" airlineCodes="" />
        <Parking index="3" type="ga" name="Ramp_start_4" lat="N49 40.738689" lon="E12 7.046068" heading="233.63"  radius="10" pushBackRoute="4" airlineCodes="" />
 </parkingList>
 <TaxiNodes>
        <node index="4" lat="N49 40.729867" lon="E12 7.029592" isOnRunway="0" holdPointType="PushBack"  />
        <node index="5" lat="N49 40.759711" lon="E12 6.996375" isOnRunway="0" holdPointType="PushBack"  />
        <node index="6" lat="N49 40.787468" lon="E12 6.969992" isOnRunway="0" holdPointType="none"  />
        <node index="7" lat="N49 40.825911" lon="E12 6.919882" isOnRunway="0" holdPointType="none"  />
        <node index="8" lat="N49 40.847599" lon="E12 6.906095" isOnRunway="0" holdPointType="PushBack"  />
        <node index="9" lat="N49 40.853063" lon="E12 6.899800" isOnRunway="0" holdPointType="none"  />
        <node index="10" lat="N49 40.857136" lon="E12 6.893359" isOnRunway="0" holdPointType="none"  />
        <node index="11" lat="N49 40.855581" lon="E12 6.888182" isOnRunway="0" holdPointType="none"  />
        <node index="12" lat="N49 40.842417" lon="E12 6.871204" isOnRunway="0" holdPointType="none"  />
        <node index="13" lat="N49 40.597815" lon="E12 7.156245" isOnRunway="0" holdPointType="none"  />
        <node index="14" lat="N49 40.593632" lon="E12 7.148453" isOnRunway="1" holdPointType="none"  />
        <node index="15" lat="N49 40.840042" lon="E12 6.872194" isOnRunway="1" holdPointType="none"  />
        <node index="16" lat="N49 40.872598" lon="E12 6.927012" isOnRunway="0" holdPointType="none"  />
        <node index="17" lat="N49 40.819533" lon="E12 7.033053" isOnRunway="0" holdPointType="PushBack"  />
        <node index="18" lat="N49 40.785702" lon="E12 7.038230" isOnRunway="0" holdPointType="none"  />
        <node index="19" lat="N49 40.754774" lon="E12 7.067909" isOnRunway="0" holdPointType="none"  />
 </TaxiNodes>
 <TaxiWaySegments>
        <arc begin="4" end="13" isPushBackRoute="0" name=""  />
        <arc begin="13" end="4" isPushBackRoute="0" name=""  />
        <arc begin="5" end="4" isPushBackRoute="0" name=""  />
        <arc begin="4" end="5" isPushBackRoute="0" name=""  />
        <arc begin="6" end="5" isPushBackRoute="0" name=""  />
        <arc begin="5" end="6" isPushBackRoute="0" name=""  />
        <arc begin="7" end="6" isPushBackRoute="0" name=""  />
        <arc begin="6" end="7" isPushBackRoute="0" name=""  />
        <arc begin="8" end="7" isPushBackRoute="0" name=""  />
        <arc begin="7" end="8" isPushBackRoute="0" name=""  />
        <arc begin="9" end="8" isPushBackRoute="0" name=""  />
        <arc begin="8" end="9" isPushBackRoute="0" name=""  />
        <arc begin="10" end="9" isPushBackRoute="0" name=""  />
        <arc begin="9" end="10" isPushBackRoute="0" name=""  />
        <arc begin="11" end="10" isPushBackRoute="0" name=""  />
        <arc begin="10" end="11" isPushBackRoute="0" name=""  />
        <arc begin="12" end="11" isPushBackRoute="0" name=""  />
        <arc begin="11" end="12" isPushBackRoute="0" name=""  />
        <arc begin="15" end="12" isPushBackRoute="0" name=""  />
        <arc begin="12" end="15" isPushBackRoute="0" name=""  />
        <arc begin="14" end="13" isPushBackRoute="0" name=""  />
        <arc begin="13" end="14" isPushBackRoute="0" name=""  />
        <arc begin="0" end="16" isPushBackRoute="1" name="Ramp_start_1"  />
        <arc begin="16" end="0" isPushBackRoute="1" name="Ramp_start_1"  />
        <arc begin="16" end="8" isPushBackRoute="1" name="Ramp_start_1"  />
        <arc begin="8" end="16" isPushBackRoute="1" name="Ramp_start_1"  />
        <arc begin="1" end="17" isPushBackRoute="1" name="Ramp_start_2"  />
        <arc begin="17" end="1" isPushBackRoute="1" name="Ramp_start_2"  />
        <arc begin="17" end="4" isPushBackRoute="1" name="Ramp_start_2"  />
        <arc begin="4" end="17" isPushBackRoute="1" name="Ramp_start_2"  />
        <arc begin="2" end="18" isPushBackRoute="1" name="Ramp_start_3"  />
        <arc begin="18" end="2" isPushBackRoute="1" name="Ramp_start_3"  />
        <arc begin="18" end="4" isPushBackRoute="1" name="Ramp_start_3"  />
        <arc begin="4" end="18" isPushBackRoute="1" name="Ramp_start_3"  />
        <arc begin="3" end="19" isPushBackRoute="1" name="Ramp_start_4"  />
        <arc begin="19" end="3" isPushBackRoute="1" name="Ramp_start_4"  />
        <arc begin="19" end="4" isPushBackRoute="1" name="Ramp_start_4"  />
        <arc begin="4" end="19" isPushBackRoute="1" name="Ramp_start_4"  />
        <arc begin="0" end="8" isPushBackRoute="1" name="Ramp_start_1"  />
        <arc begin="8" end="0" isPushBackRoute="1" name="Ramp_start_1"  />
        <arc begin="1" end="17" isPushBackRoute="1" name="Ramp_start_2"  />
        <arc begin="17" end="1" isPushBackRoute="1" name="Ramp_start_2"  />
        <arc begin="2" end="5" isPushBackRoute="1" name="Ramp_start_3"  />
        <arc begin="5" end="2" isPushBackRoute="1" name="Ramp_start_3"  />
        <arc begin="3" end="4" isPushBackRoute="1" name="Ramp_start_4"  />
        <arc begin="4" end="3" isPushBackRoute="1" name="Ramp_start_4"  />
 </TaxiWaySegments>
</groundnet>
